packetdiagram/__init__.py
packetdiagram/__init__.pyi
packetdiagram/constants.py
packetdiagram/diagram.py
packetdiagram/field.py
packetdiagram/packet.py
packetdiagram-0.0.1.dist-info/licenses/LICENSE.txt
packetdiagram-0.0.1.dist-info/METADATA
packetdiagram-0.0.1.dist-info/WHEEL
packetdiagram-0.0.1.dist-info/top_level.txt
packetdiagram-0.0.1.dist-info/RECORD
