Metadata-Version: 2.4
Name: packetdiagram
Version: 0.0.1
Summary: A tool to generate packet diagrams and save them as png or svg.
Author-email: Joram Fillol-Carlini <joram.fillolcarlini@laposte.net>
License-Expression: MIT
Project-URL: Homepage, https://github.com/JoramFC/packetdiagram
Keywords: diagram,packet,visualization
Classifier: Programming Language :: Python :: 3
Classifier: Operating System :: OS Independent
Requires-Python: >=3.9
License-File: LICENSE.txt
Requires-Dist: pycairo>=1.28.0
Dynamic: license-file
